pyblueiris/__init__.py
pyblueiris/__version__.py
pyblueiris/blueiris.py
pyblueiris/camera.py
pyblueiris/client.py
pyblueiris/const.py
pyblueiris-0.2.11.dist-info/LICENSE
pyblueiris-0.2.11.dist-info/METADATA
pyblueiris-0.2.11.dist-info/WHEEL
pyblueiris-0.2.11.dist-info/top_level.txt
pyblueiris-0.2.11.dist-info/RECORD
